stenobee/__init__.py
stenobee/metas.py
stenobee/assets/1_rawtolist_proper.py
stenobee/assets/2_convert_proper.py
stenobee/assets/3_rawtolist_proper.py
stenobee/assets/Generate_Common.py
stenobee/assets/StenoBee-Alt_Ergo_Numbers.json
stenobee/assets/StenoBee-Common.json
stenobee/assets/StenoBee-Core.json
stenobee/assets/StenoBee-Modifiers.json
stenobee/assets/StenoBee-Numbers.py
stenobee/assets/StenoBee-Proper-Nouns.json
stenobee/assets/StenoBee-Symbols&Spelling.json
stenobee/assets/StenoBeeNiche-Chemistry-[MSHTCR].json
stenobee/assets/StenoBeeNiche-Emoji-[MJ].json
stenobee/assets/StenoBeeNiche-Mathematics-[MSHTC].json
stenobee/assets/StenoBeeNiche-Minecraft-[MTCNRF].json
stenobee/assets/StenoBeeNiche-Mineral-[MLNR].json
stenobee/assets/StenoBeeNiche-ModeSetSpace-[PMSTCD].json
stenobee/assets/StenoBeeNiche-Music&Instruments-[MSTCNRD].json
stenobee/assets/StenoBeeNiche-Pokemon-[KPMN].json
stenobee/assets/extras_common.txt
stenobee/assets/overflow.txt
stenobee/assets/required_common.txt
stenobee/assets/user_list_common.txt
stenobee/assets/user_list_proper.txt
stenobee/assets/user_raw_common.txt
stenobee/assets/user_raw_proper.txt
plover_stenobee-0.8.24.dist-info/METADATA
plover_stenobee-0.8.24.dist-info/WHEEL
plover_stenobee-0.8.24.dist-info/entry_points.txt
plover_stenobee-0.8.24.dist-info/top_level.txt
plover_stenobee-0.8.24.dist-info/zip-safe
plover_stenobee-0.8.24.dist-info/RECORD
