Metadata-Version: 2.4
Name: plover-stenobee
Version: 0.8.24
Summary: Plover plugin for StenoBee Credits ( Emily Paulfioravanti Kaoffie Jen and many others )
Home-page: https://github.com/Tink-Bell/StenoBee
Author: Emily Easteal
Author-email: emily@easteal.dev
Keywords: plover plover_plugin
Classifier: Programming Language :: Python :: 3.6
Classifier: Programming Language :: Python :: 3.7
Classifier: Programming Language :: Python :: 3.8
Classifier: Programming Language :: Python :: 3.9
Requires-Dist: plover
Requires-Dist: inflect
Requires-Dist: plover-python-dictionary
